README.md
setup.py
xiaolisensor/__init__.py
xiaolisensor/light.py
xiaolisensor/sonar.py
xiaolisensor/temperature.py
xiaolisensor.egg-info/PKG-INFO
xiaolisensor.egg-info/SOURCES.txt
xiaolisensor.egg-info/dependency_links.txt
xiaolisensor.egg-info/requires.txt
xiaolisensor.egg-info/top_level.txt