Metadata-Version: 1.0
Name: xiaolisensor
Version: 0.0.9
Summary: xiaili sensors sdk
Home-page: http://xialingming
Author: lmxia
Author-email: xialingming@gmail.com
License: MIT Licence
Keywords: xiaolisensor,sdk,xialingming
Platform: any
